tofu_tree/__init__.py
tofu_tree/cli.py
tofu_tree/graph.py
tofu_tree/printer.py
tofu_tree/py.typed
tofu_tree-0.3.5.dist-info/METADATA
tofu_tree-0.3.5.dist-info/WHEEL
tofu_tree-0.3.5.dist-info/entry_points.txt
tofu_tree-0.3.5.dist-info/licenses/LICENSE
tofu_tree-0.3.5.dist-info/RECORD
