Metadata-Version: 2.4
Name: tofu-tree
Version: 0.3.5
Summary: A beautiful tree visualization tool for Terraform/OpenTofu plan output
Project-URL: Homepage, https://github.com/yourusername/tofu-tree
Project-URL: Documentation, https://github.com/yourusername/tofu-tree#readme
Project-URL: Repository, https://github.com/yourusername/tofu-tree
Project-URL: Issues, https://github.com/yourusername/tofu-tree/issues
Project-URL: Changelog, https://github.com/yourusername/tofu-tree/blob/main/CHANGELOG.md
Author-email: Mohamed Amin <your.email@example.com>
License: Hippocratic License 3.0
License-File: LICENSE
Keywords: cli,devops,iac,infrastructure,opentofu,plan,terraform,tofu,tree,visualization
Classifier: Development Status :: 4 - Beta
Classifier: Environment :: Console
Classifier: Intended Audience :: Developers
Classifier: Intended Audience :: System Administrators
Classifier: License :: Other/Proprietary License
Classifier: Operating System :: OS Independent
Classifier: Programming Language :: Python :: 3
Classifier: Programming Language :: Python :: 3.9
Classifier: Programming Language :: Python :: 3.10
Classifier: Programming Language :: Python :: 3.11
Classifier: Programming Language :: Python :: 3.12
Classifier: Programming Language :: Python :: 3.13
Classifier: Topic :: Software Development :: Libraries :: Python Modules
Classifier: Topic :: System :: Systems Administration
Classifier: Topic :: Utilities
Classifier: Typing :: Typed
Requires-Python: >=3.9
Provides-Extra: dev
Requires-Dist: mypy>=1.13; extra == 'dev'
Requires-Dist: pytest-cov>=4.0; extra == 'dev'
Requires-Dist: pytest>=8.0; extra == 'dev'
Requires-Dist: ruff>=0.8; extra == 'dev'
